xuiniaDB/HuiPornoAscii.py
xuiniaDB/__init__.py
xuiniaDB/coder_decoder.py
xuiniaDB/main.py
xuiniaDB/mainCode.py
xuiniaDB/setup.py
xuiniaDB/troll.py
xuiniaDB-1.8.dist-info/METADATA
xuiniaDB-1.8.dist-info/WHEEL
xuiniaDB-1.8.dist-info/top_level.txt
xuiniaDB-1.8.dist-info/RECORD
