Metadata-Version: 2.2
Name: xuiniaDB
Version: 1.8
Summary: EBANAIA XUETA
Requires-Dist: portableDB
Requires-Dist: colorama
Requires-Dist: opencv-python
Dynamic: description
Dynamic: requires-dist
Dynamic: summary
